{"v":"5.7.5","fr":100,"ip":0,"op":110.00000000000001,"w":300,"h":600,"nm":"Comp 1","ddd":0,"assets":[],"layers":[{"ddd":0,"ind":1,"ty":3,"nm":"","sr":1,"ks":{"o":{"a":0,"k":100,"ix":2},"r":{"a":1,"k":[{"t":0,"s":[0],"i":{"x":[0.8],"y":[1]},"o":{"x":[0.4],"y":[0]}},{"t":14,"s":[8.623299086270524],"i":{"x":[0.8],"y":[1]},"o":{"x":[0.4],"y":[0]}},{"t":32,"s":[-3.9315430514434535],"i":{"x":[0.8],"y":[1]},"o":{"x":[0.4],"y":[0]}},{"t":45,"s":[10.107746687414455],"i":{"x":[0.8],"y":[1]},"o":{"x":[0.4],"y":[0]}},{"t":62,"s":[2.2971312193268414],"i":{"x":[0.8],"y":[1]},"o":{"x":[0.4],"y":[0]}},{"t":83,"s":[7.135652517307],"i":{"x":[0.8],"y":[1]},"o":{"x":[0.4],"y":[0]}},{"t":100,"s":[0.16682869092587982],"i":{"x":[1],"y":[1]},"o":{"x":[0],"y":[0]}}],"ix":2},"p":{"a":1,"k":[{"t":0,"s":[150.00000349186513,309.83468606407547],"i":{"x":[0.8],"y":[1]},"o":{"x":[0.4],"y":[0]}},{"t":14,"s":[171.49895762014697,300.16015670634863],"i":{"x":[0.8],"y":[1]},"o":{"x":[0.4],"y":[0]}},{"t":32,"s":[137.63514231252978,298.01026129352044],"i":{"x":[0.8],"y":[1]},"o":{"x":[0.4],"y":[0]}},{"t":45,"s":[159.53873250103612,309.9716837164218],"i":{"x":[0.8],"y":[1]},"o":{"x":[0.4],"y":[0]}},{"t":62,"s":[137.41338154888768,307.69230649065514],"i":{"x":[0.8],"y":[1]},"o":{"x":[0.4],"y":[0]}},{"t":83,"s":[151.92069238854685,319.79847735917656],"i":{"x":[0.8],"y":[1]},"o":{"x":[0.4],"y":[0]}},{"t":100,"s":[148.7783603115205,309.7584993318328],"i":{"x":[1],"y":[1]},"o":{"x":[0],"y":[0]}}],"ix":2},"a":{"a":0,"k":[0,0],"ix":2},"s":{"a":0,"k":[165.29764869493195,165.29764869493195],"ix":2}},"ao":0,"ip":0,"op":110.00000000000001,"st":0,"bm":0,"hd":false},{"ddd":0,"ind":2,"ty":4,"nm":"Shape Layer 3","sr":1,"ks":{"o":{"a":0,"k":100,"ix":2},"r":{"a":0,"k":0,"ix":2},"p":{"a":0,"k":[0,0],"ix":2},"a":{"a":0,"k":[0,0],"ix":2},"s":{"a":0,"k":[100,100],"ix":2}},"ao":0,"hd":false,"parent":1,"shapes":[{"ty":"gr","hd":false,"it":[{"ty":"rc","hd":false,"d":1,"s":{"a":0,"k":[43.624990381383085,18.27414116968988],"ix":2},"p":{"a":0,"k":[0,0],"ix":2},"r":{"a":0,"k":4,"ix":2}},{"ty":"fl","c":{"a":0,"k":[1,1,1],"ix":2},"o":{"a":0,"k":100,"ix":2},"r":1,"bm":0,"nm":"Fill 1","mn":"ADBE Vector Graphic - Fill","hd":false},{"ty":"st","c":{"a":0,"k":[1,1,1],"ix":2},"o":{"a":0,"k":100,"ix":2},"w":{"a":0,"k":8,"ix":2},"hd":false},{"ty":"tm","s":{"a":0,"k":0,"ix":2},"e":{"a":0,"k":100,"ix":2},"o":{"a":0,"k":0,"ix":2},"m":1,"hd":false},{"ty":"tr","hd":false,"p":{"a":0,"k":[0,-114.98193359375003],"ix":2},"a":{"a":0,"k":[0,0],"ix":2},"s":{"a":0,"k":[100,100],"ix":2},"r":{"a":0,"k":0,"ix":2},"o":{"a":0,"k":100,"ix":2},"sk":{"a":0,"k":0,"ix":2},"sa":{"a":0,"k":0,"ix":2}}]}],"ip":0,"op":110.00000000000001,"st":0,"bm":0},{"ddd":0,"ind":3,"ty":4,"nm":"Shape Layer 2","sr":1,"ks":{"o":{"a":0,"k":100,"ix":2},"r":{"a":0,"k":0,"ix":2},"p":{"a":0,"k":[0,0],"ix":2},"a":{"a":0,"k":[0,0],"ix":2},"s":{"a":0,"k":[100,100],"ix":2}},"ao":0,"hd":false,"parent":1,"shapes":[{"ty":"gr","hd":false,"it":[{"ty":"rc","hd":false,"d":1,"s":{"a":0,"k":[43.624990381383085,169.84175224758837],"ix":2},"p":{"a":0,"k":[0,0],"ix":2},"r":{"a":0,"k":4,"ix":2}},{"ty":"fl","c":{"a":0,"k":[1,1,1],"ix":2},"o":{"a":0,"k":100,"ix":2},"r":1,"bm":0,"nm":"Fill 1","mn":"ADBE Vector Graphic - Fill","hd":false},{"ty":"st","c":{"a":0,"k":[1,1,1],"ix":2},"o":{"a":0,"k":100,"ix":2},"w":{"a":0,"k":8,"ix":2},"hd":false},{"ty":"tm","s":{"a":0,"k":0,"ix":2},"e":{"a":0,"k":100,"ix":2},"o":{"a":0,"k":0,"ix":2},"m":1,"hd":false},{"ty":"tr","hd":false,"p":{"a":0,"k":[0,-5.949676513671875],"ix":2},"a":{"a":0,"k":[0,0],"ix":2},"s":{"a":0,"k":[100,100],"ix":2},"r":{"a":0,"k":0,"ix":2},"o":{"a":0,"k":100,"ix":2},"sk":{"a":0,"k":0,"ix":2},"sa":{"a":0,"k":0,"ix":2}}]}],"ip":0,"op":110.00000000000001,"st":0,"bm":0},{"ddd":0,"ind":4,"ty":4,"nm":"Shape Layer 1","sr":1,"ks":{"o":{"a":0,"k":100,"ix":2},"r":{"a":0,"k":0,"ix":2},"p":{"a":0,"k":[0,0],"ix":2},"a":{"a":0,"k":[0,0],"ix":2},"s":{"a":0,"k":[100,100],"ix":2}},"ao":0,"hd":false,"parent":1,"shapes":[{"ty":"gr","hd":false,"it":[{"ty":"sh","hd":false,"d":1,"ks":{"a":0,"k":{"c":false,"v":[[-21.812495991966962,-17.730627684154676],[21.812488749243975,-17.730627684154676],[0,12.445465087890625],[-21.812495991966962,-17.730627684154676]],"i":[[0,0],[0,0],[0,0],[0,0]],"o":[[0,0],[0,0],[0,0],[0,0]]}}},{"ty":"fl","c":{"a":0,"k":[1,1,1],"ix":2},"o":{"a":0,"k":100,"ix":2},"r":1,"bm":0,"nm":"Fill 1","mn":"ADBE Vector Graphic - Fill","hd":false},{"ty":"st","c":{"a":0,"k":[1,1,1],"ix":2},"o":{"a":0,"k":100,"ix":2},"w":{"a":0,"k":8,"ix":2},"hd":false},{"ty":"tm","s":{"a":0,"k":0,"ix":2},"e":{"a":0,"k":100,"ix":2},"o":{"a":0,"k":0,"ix":2},"m":1,"hd":false},{"ty":"tr","hd":false,"p":{"a":0,"k":[0,111.67355346679688],"ix":2},"a":{"a":0,"k":[0,0],"ix":2},"s":{"a":0,"k":[100,100],"ix":2},"r":{"a":0,"k":0,"ix":2},"o":{"a":0,"k":100,"ix":2},"sk":{"a":0,"k":0,"ix":2},"sa":{"a":0,"k":0,"ix":2}}]}],"ip":0,"op":110.00000000000001,"st":0,"bm":0}],"markers":[]}